{
    "1000412": {
        "olx_id": 1051749570,
        "published_at": "2026-01-27T01:19:52.244390",
        "category_id": 4715,
        "price": 59.15
    },
    "1000414": {
        "olx_id": 1051749576,
        "published_at": "2026-01-27T01:20:44.096471",
        "category_id": 4715,
        "price": 69.94
    },
    "1000432": {
        "olx_id": 1051749626,
        "published_at": "2026-01-27T01:29:05.833786",
        "category_id": 4715,
        "price": 207.7
    },
    "1000449": {
        "olx_id": 1051749628,
        "published_at": "2026-01-27T01:29:55.875161",
        "category_id": 4715,
        "price": 181.04
    },
    "1000598": {
        "olx_id": 1051749657,
        "published_at": "2026-01-27T01:35:01.062560",
        "category_id": 2127,
        "price": 48.35
    }
}